setup.py
korora/__init__.py
korora.egg-info/PKG-INFO
korora.egg-info/SOURCES.txt
korora.egg-info/dependency_links.txt
korora.egg-info/top_level.txt