Metadata-Version: 1.0
Name: korora
Version: 0.0.1
Summary: korora backup
Home-page: UNKNOWN
Author: Mario Verbelen
Author-email: mario@verbelen.org
License: MIT
Platform: UNKNOWN
